famiterm/run.py
famiterm/nescpu.cpython-313-darwin.so
famiterm/nescpu.pyi
famiterm/nesapu.pyi
famiterm/__init__.py
famiterm/nesppu.pyi
famiterm/py.typed
famiterm/ssh.py
famiterm/nesapu.cpython-313-darwin.so
famiterm/nesppu.cpython-313-darwin.so
famiterm-0.2.1.dist-info/RECORD
famiterm-0.2.1.dist-info/WHEEL
famiterm-0.2.1.dist-info/entry_points.txt
famiterm-0.2.1.dist-info/top_level.txt
famiterm-0.2.1.dist-info/METADATA
famiterm-0.2.1.dist-info/licenses/LICENSE
